./LICENSE
./PKG-INFO
./README.md
./facebook_ads_mcp_complete.py
./pyproject.toml
./requirements.txt
iflow_mcp_ramsesaguirre777_facebook_ads_library_mcp-1.0.0.dist-info/METADATA
iflow_mcp_ramsesaguirre777_facebook_ads_library_mcp-1.0.0.dist-info/WHEEL
iflow_mcp_ramsesaguirre777_facebook_ads_library_mcp-1.0.0.dist-info/entry_points.txt
iflow_mcp_ramsesaguirre777_facebook_ads_library_mcp-1.0.0.dist-info/licenses/LICENSE
iflow_mcp_ramsesaguirre777_facebook_ads_library_mcp-1.0.0.dist-info/RECORD
