Metadata-Version: 2.4
Name: iflow-mcp_ramsesaguirre777-facebook-ads-library-mcp
Version: 1.0.0
Summary: Complete Facebook Ads Library MCP with 15+ advanced tools for comprehensive ad intelligence
Project-URL: Homepage, https://github.com/RamsesAguirre777/facebook-ads-library-mcp
Project-URL: Repository, https://github.com/RamsesAguirre777/facebook-ads-library-mcp
Project-URL: Issues, https://github.com/RamsesAguirre777/facebook-ads-library-mcp/issues
Author-email: RamsesAguirre777 <ramses.aguirre777@email.com>
License: MIT
License-File: LICENSE
Keywords: ads,competitive-intelligence,facebook,library,mcp
Classifier: Development Status :: 4 - Beta
Classifier: Intended Audience :: Developers
Classifier: License :: OSI Approved :: MIT License
Classifier: Programming Language :: Python :: 3
Classifier: Programming Language :: Python :: 3.8
Classifier: Programming Language :: Python :: 3.9
Classifier: Programming Language :: Python :: 3.10
Classifier: Programming Language :: Python :: 3.11
Classifier: Topic :: Software Development :: Libraries :: Python Modules
Requires-Python: >=3.8
Requires-Dist: aiohttp>=3.8.0
Requires-Dist: beautifulsoup4>=4.12.2
Requires-Dist: crawl4ai>=0.7.0
Requires-Dist: fastmcp>=2.6.1
Requires-Dist: httpx>=0.28.1
Requires-Dist: mcp>=1.9.2
Requires-Dist: numpy>=1.24.0
Requires-Dist: pandas>=2.0.0
Requires-Dist: pydantic-settings>=2.9.1
Requires-Dist: pydantic>=2.11.5
Requires-Dist: python-dotenv>=1.1.0
Requires-Dist: regex>=2023.12.25
Requires-Dist: requests>=2.32.3
Requires-Dist: selenium>=4.15.0
Requires-Dist: typing-extensions>=4.14.0
Provides-Extra: dev
Requires-Dist: black>=23.0.0; extra == 'dev'
Requires-Dist: flake8>=6.0.0; extra == 'dev'
Requires-Dist: pytest>=7.4.0; extra == 'dev'
